osp/__init__.py
osp/core/__init__.py
osp/core/cuds.py
osp/core/namespaces.py
osp/core/neighbor_dict.py
osp/core/packageinfo.py
osp/core/pico.py
osp/core/warnings.py
osp/core/ontology/__init__.py
osp/core/ontology/attribute.py
osp/core/ontology/cuba.py
osp/core/ontology/datatypes.py
osp/core/ontology/entity.py
osp/core/ontology/installation.py
osp/core/ontology/namespace.py
osp/core/ontology/namespace_registry.py
osp/core/ontology/oclass.py
osp/core/ontology/oclass_composition.py
osp/core/ontology/oclass_restriction.py
osp/core/ontology/ontology.py
osp/core/ontology/relationship.py
osp/core/ontology/docs/__init__.py
osp/core/ontology/docs/city.ontology.yml
osp/core/ontology/docs/cuba.ttl
osp/core/ontology/docs/dcat2.yml
osp/core/ontology/docs/dcmitype.yml
osp/core/ontology/docs/dcterms.yml
osp/core/ontology/docs/emmo-datamodel.yml
osp/core/ontology/docs/emmo.yml
osp/core/ontology/docs/foaf.yml
osp/core/ontology/docs/parser_test.ontology.yml
osp/core/ontology/docs/prov.yml
osp/core/ontology/parser/__init__.py
osp/core/ontology/parser/parser.py
osp/core/ontology/parser/owl/__init__.py
osp/core/ontology/parser/owl/keywords.py
osp/core/ontology/parser/owl/parser.py
osp/core/ontology/parser/yml/__init__.py
osp/core/ontology/parser/yml/case_insensitivity.py
osp/core/ontology/parser/yml/keywords.py
osp/core/ontology/parser/yml/parser.py
osp/core/ontology/parser/yml/validator.py
osp/core/session/__init__.py
osp/core/session/buffers.py
osp/core/session/core_session.py
osp/core/session/file_wrapper_session.py
osp/core/session/registry.py
osp/core/session/result.py
osp/core/session/session.py
osp/core/session/sim_wrapper_session.py
osp/core/session/sparql_backend.py
osp/core/session/wrapper_session.py
osp/core/session/db/__init__.py
osp/core/session/db/db_wrapper_session.py
osp/core/session/db/sql_migrate.py
osp/core/session/db/sql_util.py
osp/core/session/db/sql_wrapper_session.py
osp/core/session/db/triplestore_wrapper_session.py
osp/core/session/transport/__init__.py
osp_core-3.9.0.dist-info/LICENSE.md
osp_core-3.9.0.dist-info/METADATA
osp_core-3.9.0.dist-info/WHEEL
osp_core-3.9.0.dist-info/entry_points.txt
osp_core-3.9.0.dist-info/top_level.txt
osp_core-3.9.0.dist-info/RECORD
