Metadata-Version: 2.1
Name: osp-core
Version: 3.9.0
Summary: The native implementation of the SimPhoNy CUDS objects
Home-page: https://github.com/simphony
Download-URL: https://pypi.python.org/pypi/osp-core
Author: SimPhoNy, EU FP7 Project (Nr. 604005)
Maintainer: Fraunhofer IWM
Maintainer-email: simphony@iwm.fraunhofer.de
License: BSD-3-Clause
Project-URL: Tracker, https://github.com/simphony/osp-core/issues
Project-URL: Documentation, https://simphony.readthedocs.io
Project-URL: Source, https://github.com/simphony/osp-core
Keywords: owl ontology interoperability materials-science osp simphony wrappers cuds open-simulation-platform
Classifier: Development Status :: 5 - Production/Stable
Classifier: Intended Audience :: Developers
Classifier: Intended Audience :: Science/Research
Classifier: Topic :: Scientific/Engineering
Classifier: Topic :: Software Development :: Libraries
Classifier: License :: OSI Approved :: BSD License
Classifier: Programming Language :: Python
Classifier: Programming Language :: Python :: 3 :: Only
Classifier: Programming Language :: Python :: 3.6
Classifier: Programming Language :: Python :: 3.7
Classifier: Programming Language :: Python :: 3.8
Classifier: Operating System :: Microsoft :: Windows
Classifier: Operating System :: MacOS
Classifier: Operating System :: Unix
Requires-Python: >=3.6
License-File: LICENSE.md
Requires-Dist: graphviz
Requires-Dist: numpy
Requires-Dist: PyYaml
Requires-Dist: requests
Requires-Dist: websockets (<11,>=9)
Requires-Dist: pyparsing (<3.0.0) ; python_version < "3.7"
Requires-Dist: rdflib (<6.0.0,>=5.0.0) ; python_version < "3.7"
Requires-Dist: rdflib-jsonld (==0.6.1) ; python_version < "3.7"
Requires-Dist: websockets (>=10) ; python_version >= "3.10"
Requires-Dist: rdflib (<7.0.0,>=6.0.0) ; python_version >= "3.7"
